pyroll/sparling_spreading.py
pyroll_sparling_spreading-3.0.0.dist-info/METADATA
pyroll_sparling_spreading-3.0.0.dist-info/WHEEL
pyroll_sparling_spreading-3.0.0.dist-info/licenses/LICENSE
pyroll_sparling_spreading-3.0.0.dist-info/RECORD
