Metadata-Version: 2.3
Name: pyroll-sparling-spreading
Version: 3.0.0
Summary: Plugin for PyRolL providing spreading claclulation using Sparling's equation.
Project-URL: Homepage, https://pyroll-project.github.io
Project-URL: Repository, https://github.com/pyroll-project/pyroll-sparling-spreading
Project-URL: Documentation, https://github.com/pyroll-project/pyroll-sparling-spreading/blob/main/docs/docs.pdf
Author-email: Christoph Renzing <christoph.renzing@imf.tu-freiberg.de>, Max Weiner <max.weiner@imf.tu-freiberg.de>
License-Expression: BSD-3-Clause
License-File: LICENSE
Classifier: Intended Audience :: Manufacturing
Classifier: Intended Audience :: Science/Research
Classifier: Operating System :: OS Independent
Classifier: Topic :: Scientific/Engineering
Requires-Python: <4.0,>=3.9
Requires-Dist: pyroll-core~=3.0
Provides-Extra: pillar-model
Requires-Dist: pyroll-pillar-model~=3.0; extra == 'pillar-model'
